ai_cli/__init__.py
ai_cli/agent.py
ai_cli/cli.py
ai_cli/client.py
ai_cli/code_parser.py
ai_cli/models.py
ai_cli/prompt_manager.py
ai_cli/resource_monitor.py
ai_cli/types.py
ai_offline_cli-0.1.1.dist-info/METADATA
ai_offline_cli-0.1.1.dist-info/WHEEL
ai_offline_cli-0.1.1.dist-info/entry_points.txt
ai_offline_cli-0.1.1.dist-info/top_level.txt
ai_offline_cli-0.1.1.dist-info/RECORD
