Metadata-Version: 2.4
Name: ai-offline-cli
Version: 0.1.1
Summary: Offline AI assistant for code writing, command execution, and chat working with any offline models
Author: AI CLI Team
License: MIT
Classifier: Programming Language :: Python :: 3
Classifier: Programming Language :: Python :: 3.11
Classifier: Operating System :: OS Independent
Classifier: Development Status :: 3 - Alpha
Classifier: Intended Audience :: Developers
Classifier: Topic :: Software Development :: Libraries :: Python Modules
Classifier: Topic :: Scientific/Engineering :: Artificial Intelligence
Requires-Python: >=3.11
Requires-Dist: httpx>=0.27.0
Requires-Dist: pydantic>=2.0.0
Requires-Dist: psutil>=5.9.0
Provides-Extra: llama-cpp
Requires-Dist: llama-cpp-python; extra == "llama-cpp"
Provides-Extra: gpu
Requires-Dist: pynvml; extra == "gpu"
Provides-Extra: all
Requires-Dist: llama-cpp-python; extra == "all"
Requires-Dist: pynvml; extra == "all"
Dynamic: author
Dynamic: classifier
Dynamic: description
Dynamic: description-content-type
Dynamic: license
Dynamic: provides-extra
Dynamic: requires-dist
Dynamic: requires-python
Dynamic: summary
